pyranha-0.10.data/purelib/pyranha/__init__.py
pyranha-0.10.data/purelib/pyranha/_common.py
pyranha-0.10.data/purelib/pyranha/_core.pyd
pyranha-0.10.data/purelib/pyranha/_version.py
pyranha-0.10.data/purelib/pyranha/celmec.py
pyranha-0.10.data/purelib/pyranha/libboost_bzip2-mgw62-mt-1_63.dll
pyranha-0.10.data/purelib/pyranha/libboost_iostreams-mgw62-mt-1_63.dll
pyranha-0.10.data/purelib/pyranha/libboost_python3-mgw62-mt-1_63.dll
pyranha-0.10.data/purelib/pyranha/libboost_serialization-mgw62-mt-1_63.dll
pyranha-0.10.data/purelib/pyranha/libboost_zlib-mgw62-mt-1_63.dll
pyranha-0.10.data/purelib/pyranha/libgcc_s_seh-1.dll
pyranha-0.10.data/purelib/pyranha/libstdc++-6.dll
pyranha-0.10.data/purelib/pyranha/libwinpthread-1.dll
pyranha-0.10.data/purelib/pyranha/math.py
pyranha-0.10.data/purelib/pyranha/test.py
pyranha-0.10.data/purelib/pyranha/types.py
pyranha-0.10.data/purelib/pyranha/_tutorial/__init__.py
pyranha-0.10.data/purelib/pyranha/_tutorial/hello_piranha.py
pyranha-0.10.data/purelib/pyranha/_tutorial/integer.py
pyranha-0.10.data/purelib/pyranha/_tutorial/rational.py
pyranha-0.10.dist-info/DESCRIPTION.rst
pyranha-0.10.dist-info/METADATA
pyranha-0.10.dist-info/RECORD
pyranha-0.10.dist-info/WHEEL
pyranha-0.10.dist-info/metadata.json
pyranha-0.10.dist-info/top_level.txt
