Metadata-Version: 2.0
Name: pyranha
Version: 0.10
Summary: A computer algebra system for celestial mechanics
Home-page: https://github.com/bluescarni/piranha
Author: Francesco Biscani
Author-email: bluescarni@gmail.com
License: GPLv3+/LGPL3+
Keywords: computer_algebra CAS science math physics astronomy
Platform: Unix
Platform: Windows
Platform: OSX
Classifier: Development Status :: 4 - Beta
Classifier: Operating System :: OS Independent
Classifier: Intended Audience :: Science/Research
Classifier: Topic :: Scientific/Engineering
Classifier: Topic :: Scientific/Engineering :: Astronomy
Classifier: Topic :: Scientific/Engineering :: Mathematics
Classifier: Topic :: Scientific/Engineering :: Physics
Classifier: License :: OSI Approved :: GNU General Public License v3 or later (GPLv3+)
Classifier: License :: OSI Approved :: GNU Lesser General Public License v3 or later (LGPLv3+)
Classifier: Programming Language :: Python :: 2
Classifier: Programming Language :: Python :: 3
Requires-Dist: mpmath
Requires-Dist: numpy
